LICENSE
MANIFEST.in
README.md
poetry.lock
pyproject.toml
setup.cfg
setup.py
proxyhub/__init__.py
proxyhub/__main__.py
proxyhub/api.py
proxyhub/checker.py
proxyhub/cli.py
proxyhub/errors.py
proxyhub/judge.py
proxyhub/negotiators.py
proxyhub/providers.py
proxyhub/proxy.py
proxyhub/resolver.py
proxyhub/server.py
proxyhub/utils.py
proxyhub.egg-info/PKG-INFO
proxyhub.egg-info/SOURCES.txt
proxyhub.egg-info/dependency_links.txt
proxyhub.egg-info/entry_points.txt
proxyhub.egg-info/not-zip-safe
proxyhub.egg-info/requires.txt
proxyhub.egg-info/top_level.txt
proxyhub/data/GeoLite2-Country.mmdb
proxyhub/data/__init__.py
tests/test_negotiators.py
tests/test_proxy.py
tests/test_resolver.py
tests/test_utils.py