Metadata-Version: 2.1
Name: proxyhub
Version: 0.0.1a5
Summary: An advanced [Finder | Checker | Server] tool for proxy servers, supporting both HTTP(S) and SOCKS protocols.
Home-page: https://github.com/ForceFledgling/proxyhub
Author: ForceFledgling
Author-email: pvenv@icloud.com
License: Apache License, Version 2.0
Keywords: proxy finder grabber scraper parser graber scrapper checker broker async asynchronous http https connect socks socks4 socks5
Platform: any
Classifier: Development Status :: 5 - Production/Stable
Classifier: Environment :: Console
Classifier: Environment :: Web Environment
Classifier: Intended Audience :: Developers
Classifier: Programming Language :: Python :: 3.5
Classifier: Programming Language :: Python :: 3.6
Classifier: Programming Language :: Python :: 3.7
Classifier: Programming Language :: Python :: 3.8
Classifier: Operating System :: POSIX
Classifier: Operating System :: MacOS :: MacOS X
Classifier: Operating System :: Microsoft :: Windows
Classifier: Topic :: Internet :: WWW/HTTP :: Indexing/Search
Classifier: Topic :: Internet :: Proxy Servers
Classifier: License :: OSI Approved :: Apache Software License
Requires-Python: >=3.5.3
License-File: LICENSE
Requires-Dist: aiohttp>=3.5.4
Requires-Dist: aiodns>=2.0.0
Requires-Dist: attrs==19.3.0
Requires-Dist: maxminddb>=1.4.1
Requires-Dist: cachetools==4.1.0
